pyhatching/__init__.py
pyhatching/__main__.py
pyhatching/_args.py
pyhatching/_cmds.py
pyhatching/base.py
pyhatching/enums.py
pyhatching/errors.py
pyhatching/utils.py
pyhatching-0.2.1.dist-info/LICENSE
pyhatching-0.2.1.dist-info/METADATA
pyhatching-0.2.1.dist-info/WHEEL
pyhatching-0.2.1.dist-info/entry_points.txt
pyhatching-0.2.1.dist-info/top_level.txt
pyhatching-0.2.1.dist-info/RECORD
