Metadata-Version: 2.1
Name: pyhatching
Version: 0.2.1
Summary: An async Python client for the Hatching Triage Sandbox.
Author: John Gorman
License: MIT License
Project-URL: Homepage, https://github.com/gormaniac/pyhatching
Project-URL: Documentation, https://gormo.co/pyhatching/
Requires-Python: >=3.11
License-File: LICENSE
Requires-Dist: aiohttp ==3.8.4
Requires-Dist: pydantic ==1.10.7
